README.md
setup.py
atomic_queue.egg-info/PKG-INFO
atomic_queue.egg-info/SOURCES.txt
atomic_queue.egg-info/dependency_links.txt
atomic_queue.egg-info/requires.txt
atomic_queue.egg-info/top_level.txt
atomicqueue/__init__.py
atomicqueue/barrier.py
atomicqueue/event_processor.py
atomicqueue/exceptions.py
atomicqueue/queue.py
atomicqueue/ring_buffer.py
atomicqueue/sequencer.py
atomicqueue/wait_strategy.py
perf_tests/__init__.py
perf_tests/test_speed.py
tests/__init__.py
tests/test_atomic_queue.py
tests/test_ring_buffer.py