Metadata-Version: 2.1
Name: atomic-queue
Version: 1.0.0
Summary: A lock-free, thread-safe queue using the C++ atomic library to synchronise memory access.
Home-page: https://github.com/arossoshynskyy/atomic-queue
Author: Andriy Rossoshynskyy
Author-email: andriy.rossoshynskyy@gmail.com
License: UNKNOWN
Platform: UNKNOWN
Classifier: Programming Language :: Python :: 3
Classifier: License :: OSI Approved :: MIT License
Requires-Python: >=3.6
